deleter/__init__.py
deleter/__main__.py
deleter/core.py
deleter/deleters.py
deleter/util.py
deleter-0.1.1.dist-info/LICENSE
deleter-0.1.1.dist-info/METADATA
deleter-0.1.1.dist-info/WHEEL
deleter-0.1.1.dist-info/entry_points.txt
deleter-0.1.1.dist-info/top_level.txt
deleter-0.1.1.dist-info/RECORD
